djangoapprove/__init__.py
djangoapprove/mixins.py
djangoapprove/models.py
djangoapprove/settings.py
djangoapprove/tests/__init__.py
djangoapprove/tests/test_approval.py
djangoapprove/tests/test_djangoapprove.py
djangoapprove-0.2.0.dist-info/LICENSE
djangoapprove-0.2.0.dist-info/METADATA
djangoapprove-0.2.0.dist-info/WHEEL
djangoapprove-0.2.0.dist-info/top_level.txt
djangoapprove-0.2.0.dist-info/RECORD
