Metadata-Version: 2.1
Name: djangoapprove
Version: 0.2.0
Summary: A Django module to manage approval workflows for CRUD operations.
Home-page: https://github.com/ullauri/djangoapprove
Author: Byron Cabrera
Author-email: byron.o.cabrera@gmail.com
License: MIT
Project-URL: Source, https://github.com/ullauri/djangoapprove
Keywords: django,approvals,workflow,CRUD
Requires-Python: >=3.7
License-File: LICENSE
Requires-Dist: asgiref ==3.8.1
Requires-Dist: Django ==5.1.3
Requires-Dist: sqlparse ==0.5.1
Requires-Dist: typing-extensions ==4.12.2
